Metadata-Version: 2.1
Name: ducttape-calpads
Version: 0.4.0
Summary: Extension of the duct-tape package to automate CALPADS data extraction
Home-page: https://github.com/SummitPublicSchools/ducttape-calpads
Author: Yusuph Mkangara
Author-email: ymkangara@summitps.org
License:                     GNU GENERAL PUBLIC LICENSE
License-File: LICENSE
